[
    {
        "task_duration": {
            "start": "2023-12-10 00:03:02.211487",
            "duration": "0:00:28.553907",
            "radar_time": null,
            "sat_time": null,
            "status": "failed",
            "error_msg": "550 Failed to change directory."
        }
    },
    {
        "task_duration": {
            "start": "2023-12-10 00:13:02.402945",
            "duration": "0:06:56.733356",
            "radar_time": "2023-12-10 00:10:00",
            "sat_time": null,
            "status": "done",
            "error_msg": null
        }
    },
    {
        "task_duration": {
            "start": "2023-12-10 00:23:03.073846",
            "duration": "0:06:39.798978",
            "radar_time": "2023-12-10 00:20:00",
            "sat_time": null,
            "status": "done",
            "error_msg": null
        }
    },
    {
        "task_duration": {
            "start": "2023-12-10 00:33:02.813072",
            "duration": "0:06:41.462959",
            "radar_time": "2023-12-10 00:30:00",
            "sat_time": null,
            "status": "done",
            "error_msg": null
        }
    },
    {
        "task_duration": {
            "start": "2023-12-10 00:43:03.103562",
            "duration": "0:06:34.971858",
            "radar_time": "2023-12-10 00:40:00",
            "sat_time": null,
            "status": "done",
            "error_msg": null
        }
    },
    {
        "task_duration": {
            "start": "2023-12-10 00:53:02.994048",
            "duration": "0:06:37.552435",
            "radar_time": "2023-12-10 00:50:00",
            "sat_time": null,
            "status": "done",
            "error_msg": null
        }
    },
    {
        "task_duration": {
            "start": "2023-12-10 01:03:02.427831",
            "duration": "0:06:55.947421",
            "radar_time": "2023-12-10 01:00:00",
            "sat_time": null,
            "status": "done",
            "error_msg": null
        }
    },
    {
        "task_duration": {
            "start": "2023-12-10 01:13:02.309563",
            "duration": "0:06:51.014465",
            "radar_time": "2023-12-10 01:10:00",
            "sat_time": null,
            "status": "done",
            "error_msg": null
        }
    },
    {
        "task_duration": {
            "start": "2023-12-10 01:23:03.198807",
            "duration": "0:06:49.763700",
            "radar_time": "2023-12-10 01:20:00",
            "sat_time": null,
            "status": "done",
            "error_msg": null
        }
    },
    {
        "task_duration": {
            "start": "2023-12-10 01:33:02.890942",
            "duration": "0:07:02.958414",
            "radar_time": "2023-12-10 01:30:00",
            "sat_time": null,
            "status": "done",
            "error_msg": null
        }
    },
    {
        "task_duration": {
            "start": "2023-12-10 01:43:02.791668",
            "duration": "0:06:18.207686",
            "radar_time": "2023-12-10 01:40:00",
            "sat_time": null,
            "status": "done",
            "error_msg": null
        }
    },
    {
        "task_duration": {
            "start": "2023-12-10 01:53:02.902556",
            "duration": "0:06:54.227244",
            "radar_time": "2023-12-10 01:50:00",
            "sat_time": null,
            "status": "done",
            "error_msg": null
        }
    },
    {
        "task_duration": {
            "start": "2023-12-10 02:03:02.200453",
            "duration": "0:07:04.206765",
            "radar_time": "2023-12-10 02:00:00",
            "sat_time": null,
            "status": "done",
            "error_msg": null
        }
    },
    {
        "task_duration": {
            "start": "2023-12-10 02:13:02.344545",
            "duration": "0:06:39.489287",
            "radar_time": "2023-12-10 02:10:00",
            "sat_time": null,
            "status": "done",
            "error_msg": null
        }
    },
    {
        "task_duration": {
            "start": "2023-12-10 02:23:02.768843",
            "duration": "0:06:36.575010",
            "radar_time": "2023-12-10 02:20:00",
            "sat_time": null,
            "status": "done",
            "error_msg": null
        }
    },
    {
        "task_duration": {
            "start": "2023-12-10 02:33:03.233688",
            "duration": "0:06:51.144261",
            "radar_time": "2023-12-10 02:30:00",
            "sat_time": null,
            "status": "done",
            "error_msg": null
        }
    },
    {
        "task_duration": {
            "start": "2023-12-10 02:43:02.274546",
            "duration": "0:06:36.730794",
            "radar_time": "2023-12-10 02:40:00",
            "sat_time": null,
            "status": "done",
            "error_msg": null
        }
    },
    {
        "task_duration": {
            "start": "2023-12-10 02:53:02.994906",
            "duration": "0:06:33.865139",
            "radar_time": "2023-12-10 02:50:00",
            "sat_time": null,
            "status": "done",
            "error_msg": null
        }
    },
    {
        "task_duration": {
            "start": "2023-12-10 03:03:02.824781",
            "duration": "0:06:35.393484",
            "radar_time": "2023-12-10 03:00:00",
            "sat_time": null,
            "status": "done",
            "error_msg": null
        }
    },
    {
        "task_duration": {
            "start": "2023-12-10 03:13:03.061049",
            "duration": "0:06:53.846575",
            "radar_time": "2023-12-10 03:10:00",
            "sat_time": null,
            "status": "done",
            "error_msg": null
        }
    },
    {
        "task_duration": {
            "start": "2023-12-10 03:23:02.890675",
            "duration": "0:06:33.165358",
            "radar_time": "2023-12-10 03:20:00",
            "sat_time": null,
            "status": "done",
            "error_msg": null
        }
    },
    {
        "task_duration": {
            "start": "2023-12-10 03:33:02.985755",
            "duration": "0:06:56.055263",
            "radar_time": "2023-12-10 03:30:00",
            "sat_time": null,
            "status": "done",
            "error_msg": null
        }
    },
    {
        "task_duration": {
            "start": "2023-12-10 03:43:03.170517",
            "duration": "0:06:50.214056",
            "radar_time": "2023-12-10 03:40:00",
            "sat_time": null,
            "status": "done",
            "error_msg": null
        }
    },
    {
        "task_duration": {
            "start": "2023-12-10 03:53:02.649403",
            "duration": "0:06:57.325871",
            "radar_time": "2023-12-10 03:50:00",
            "sat_time": null,
            "status": "done",
            "error_msg": null
        }
    },
    {
        "task_duration": {
            "start": "2023-12-10 04:03:02.730877",
            "duration": "0:06:32.999654",
            "radar_time": "2023-12-10 04:00:00",
            "sat_time": null,
            "status": "done",
            "error_msg": null
        }
    },
    {
        "task_duration": {
            "start": "2023-12-10 04:13:02.633806",
            "duration": "0:06:30.427006",
            "radar_time": "2023-12-10 04:10:00",
            "sat_time": null,
            "status": "done",
            "error_msg": null
        }
    },
    {
        "task_duration": {
            "start": "2023-12-10 04:23:03.016019",
            "duration": "0:06:35.785985",
            "radar_time": "2023-12-10 04:20:00",
            "sat_time": null,
            "status": "done",
            "error_msg": null
        }
    },
    {
        "task_duration": {
            "start": "2023-12-10 04:33:02.951095",
            "duration": "0:06:55.446722",
            "radar_time": "2023-12-10 04:30:00",
            "sat_time": null,
            "status": "done",
            "error_msg": null
        }
    },
    {
        "task_duration": {
            "start": "2023-12-10 04:43:02.376248",
            "duration": "0:06:36.828389",
            "radar_time": "2023-12-10 04:40:00",
            "sat_time": null,
            "status": "done",
            "error_msg": null
        }
    },
    {
        "task_duration": {
            "start": "2023-12-10 04:53:03.105645",
            "duration": "0:06:57.616211",
            "radar_time": "2023-12-10 04:50:00",
            "sat_time": null,
            "status": "done",
            "error_msg": null
        }
    },
    {
        "task_duration": {
            "start": "2023-12-10 05:03:02.593159",
            "duration": "0:06:32.271820",
            "radar_time": "2023-12-10 05:00:00",
            "sat_time": null,
            "status": "done",
            "error_msg": null
        }
    },
    {
        "task_duration": {
            "start": "2023-12-10 05:13:02.819507",
            "duration": "0:06:35.367673",
            "radar_time": "2023-12-10 05:10:00",
            "sat_time": null,
            "status": "done",
            "error_msg": null
        }
    },
    {
        "task_duration": {
            "start": "2023-12-10 05:23:03.112757",
            "duration": "0:06:33.938789",
            "radar_time": "2023-12-10 05:20:00",
            "sat_time": null,
            "status": "done",
            "error_msg": null
        }
    },
    {
        "task_duration": {
            "start": "2023-12-10 05:33:03.000766",
            "duration": "0:06:53.969435",
            "radar_time": "2023-12-10 05:30:00",
            "sat_time": null,
            "status": "done",
            "error_msg": null
        }
    },
    {
        "task_duration": {
            "start": "2023-12-10 05:43:03.126417",
            "duration": "0:06:45.604263",
            "radar_time": "2023-12-10 05:40:00",
            "sat_time": null,
            "status": "done",
            "error_msg": null
        }
    },
    {
        "task_duration": {
            "start": "2023-12-10 05:53:02.717002",
            "duration": "0:06:31.808460",
            "radar_time": "2023-12-10 05:50:00",
            "sat_time": null,
            "status": "done",
            "error_msg": null
        }
    },
    {
        "task_duration": {
            "start": "2023-12-10 06:03:02.296003",
            "duration": "0:07:03.024921",
            "radar_time": "2023-12-10 06:00:00",
            "sat_time": null,
            "status": "done",
            "error_msg": null
        }
    },
    {
        "task_duration": {
            "start": "2023-12-10 06:13:02.352753",
            "duration": "0:06:37.263926",
            "radar_time": "2023-12-10 06:10:00",
            "sat_time": null,
            "status": "done",
            "error_msg": null
        }
    },
    {
        "task_duration": {
            "start": "2023-12-10 06:23:02.810996",
            "duration": "0:06:50.750124",
            "radar_time": "2023-12-10 06:20:00",
            "sat_time": null,
            "status": "done",
            "error_msg": null
        }
    },
    {
        "task_duration": {
            "start": "2023-12-10 06:33:02.529960",
            "duration": "0:06:58.982154",
            "radar_time": "2023-12-10 06:30:00",
            "sat_time": null,
            "status": "done",
            "error_msg": null
        }
    },
    {
        "task_duration": {
            "start": "2023-12-10 06:43:02.502553",
            "duration": "0:06:57.563523",
            "radar_time": "2023-12-10 06:40:00",
            "sat_time": null,
            "status": "done",
            "error_msg": null
        }
    },
    {
        "task_duration": {
            "start": "2023-12-10 06:53:03.094219",
            "duration": "0:06:32.233715",
            "radar_time": "2023-12-10 06:50:00",
            "sat_time": null,
            "status": "done",
            "error_msg": null
        }
    },
    {
        "task_duration": {
            "start": "2023-12-10 07:03:02.260030",
            "duration": "0:06:50.762517",
            "radar_time": "2023-12-10 07:00:00",
            "sat_time": null,
            "status": "done",
            "error_msg": null
        }
    },
    {
        "task_duration": {
            "start": "2023-12-10 07:13:02.992844",
            "duration": "0:06:56.582175",
            "radar_time": "2023-12-10 07:10:00",
            "sat_time": null,
            "status": "done",
            "error_msg": null
        }
    },
    {
        "task_duration": {
            "start": "2023-12-10 07:23:02.641213",
            "duration": "0:06:50.019962",
            "radar_time": "2023-12-10 07:20:00",
            "sat_time": null,
            "status": "done",
            "error_msg": null
        }
    },
    {
        "task_duration": {
            "start": "2023-12-10 07:33:02.746704",
            "duration": "0:06:05.267677",
            "radar_time": "2023-12-10 07:30:00",
            "sat_time": null,
            "status": "done",
            "error_msg": null
        }
    },
    {
        "task_duration": {
            "start": "2023-12-10 07:43:03.159146",
            "duration": "0:06:41.323845",
            "radar_time": "2023-12-10 07:40:00",
            "sat_time": null,
            "status": "done",
            "error_msg": null
        }
    },
    {
        "task_duration": {
            "start": "2023-12-10 07:53:02.602716",
            "duration": "0:06:56.571830",
            "radar_time": "2023-12-10 07:50:00",
            "sat_time": null,
            "status": "done",
            "error_msg": null
        }
    },
    {
        "task_duration": {
            "start": "2023-12-10 08:03:03.131714",
            "duration": "0:07:18.586843",
            "radar_time": "2023-12-10 08:00:00",
            "sat_time": null,
            "status": "done",
            "error_msg": null
        }
    },
    {
        "task_duration": {
            "start": "2023-12-10 08:13:02.668616",
            "duration": "0:06:36.813650",
            "radar_time": "2023-12-10 08:10:00",
            "sat_time": null,
            "status": "done",
            "error_msg": null
        }
    },
    {
        "task_duration": {
            "start": "2023-12-10 08:23:02.562487",
            "duration": "0:06:04.993672",
            "radar_time": "2023-12-10 08:20:00",
            "sat_time": null,
            "status": "done",
            "error_msg": null
        }
    },
    {
        "task_duration": {
            "start": "2023-12-10 08:33:02.619199",
            "duration": "0:06:56.303716",
            "radar_time": "2023-12-10 08:30:00",
            "sat_time": null,
            "status": "done",
            "error_msg": null
        }
    },
    {
        "task_duration": {
            "start": "2023-12-10 08:43:03.109339",
            "duration": "0:06:37.775325",
            "radar_time": "2023-12-10 08:40:00",
            "sat_time": null,
            "status": "done",
            "error_msg": null
        }
    },
    {
        "task_duration": {
            "start": "2023-12-10 08:53:02.887270",
            "duration": "0:06:33.444121",
            "radar_time": "2023-12-10 08:50:00",
            "sat_time": null,
            "status": "done",
            "error_msg": null
        }
    },
    {
        "task_duration": {
            "start": "2023-12-10 09:03:02.353582",
            "duration": "0:06:51.287072",
            "radar_time": "2023-12-10 09:00:00",
            "sat_time": null,
            "status": "done",
            "error_msg": null
        }
    },
    {
        "task_duration": {
            "start": "2023-12-10 09:13:02.795745",
            "duration": "0:06:52.884486",
            "radar_time": "2023-12-10 09:10:00",
            "sat_time": null,
            "status": "done",
            "error_msg": null
        }
    },
    {
        "task_duration": {
            "start": "2023-12-10 09:23:02.743775",
            "duration": "0:06:27.587321",
            "radar_time": "2023-12-10 09:20:00",
            "sat_time": null,
            "status": "done",
            "error_msg": null
        }
    },
    {
        "task_duration": {
            "start": "2023-12-10 09:33:02.359265",
            "duration": "0:06:54.612988",
            "radar_time": "2023-12-10 09:30:00",
            "sat_time": null,
            "status": "done",
            "error_msg": null
        }
    },
    {
        "task_duration": {
            "start": "2023-12-10 09:43:02.948724",
            "duration": "0:06:36.315101",
            "radar_time": "2023-12-10 09:40:00",
            "sat_time": null,
            "status": "done",
            "error_msg": null
        }
    },
    {
        "task_duration": {
            "start": "2023-12-10 09:53:02.235809",
            "duration": "0:06:38.721918",
            "radar_time": "2023-12-10 09:50:00",
            "sat_time": null,
            "status": "done",
            "error_msg": null
        }
    },
    {
        "task_duration": {
            "start": "2023-12-10 10:03:03.107397",
            "duration": "0:07:03.875414",
            "radar_time": "2023-12-10 10:00:00",
            "sat_time": null,
            "status": "done",
            "error_msg": null
        }
    },
    {
        "task_duration": {
            "start": "2023-12-10 10:13:02.916078",
            "duration": "0:06:41.034735",
            "radar_time": "2023-12-10 10:10:00",
            "sat_time": null,
            "status": "done",
            "error_msg": null
        }
    },
    {
        "task_duration": {
            "start": "2023-12-10 10:23:02.956032",
            "duration": "0:06:37.205585",
            "radar_time": "2023-12-10 10:20:00",
            "sat_time": null,
            "status": "done",
            "error_msg": null
        }
    },
    {
        "task_duration": {
            "start": "2023-12-10 10:33:02.969417",
            "duration": "0:06:49.960826",
            "radar_time": "2023-12-10 10:30:00",
            "sat_time": null,
            "status": "done",
            "error_msg": null
        }
    },
    {
        "task_duration": {
            "start": "2023-12-10 10:43:03.020761",
            "duration": "0:06:55.049362",
            "radar_time": "2023-12-10 10:40:00",
            "sat_time": null,
            "status": "done",
            "error_msg": null
        }
    },
    {
        "task_duration": {
            "start": "2023-12-10 10:53:03.118113",
            "duration": "0:06:33.125566",
            "radar_time": "2023-12-10 10:50:00",
            "sat_time": null,
            "status": "done",
            "error_msg": null
        }
    },
    {
        "task_duration": {
            "start": "2023-12-10 11:03:02.235928",
            "duration": "0:06:36.498606",
            "radar_time": "2023-12-10 11:00:00",
            "sat_time": null,
            "status": "done",
            "error_msg": null
        }
    },
    {
        "task_duration": {
            "start": "2023-12-10 11:13:02.871526",
            "duration": "0:06:35.926663",
            "radar_time": "2023-12-10 11:10:00",
            "sat_time": null,
            "status": "done",
            "error_msg": null
        }
    },
    {
        "task_duration": {
            "start": "2023-12-10 11:23:02.560425",
            "duration": "0:06:37.386196",
            "radar_time": "2023-12-10 11:20:00",
            "sat_time": null,
            "status": "done",
            "error_msg": null
        }
    },
    {
        "task_duration": {
            "start": "2023-12-10 11:33:03.023979",
            "duration": "0:06:19.149695",
            "radar_time": "2023-12-10 11:30:00",
            "sat_time": null,
            "status": "done",
            "error_msg": null
        }
    },
    {
        "task_duration": {
            "start": "2023-12-10 11:43:03.125641",
            "duration": "0:06:19.314514",
            "radar_time": "2023-12-10 11:40:00",
            "sat_time": null,
            "status": "done",
            "error_msg": null
        }
    },
    {
        "task_duration": {
            "start": "2023-12-10 11:53:02.406620",
            "duration": "0:06:32.500920",
            "radar_time": "2023-12-10 11:50:00",
            "sat_time": null,
            "status": "done",
            "error_msg": null
        }
    },
    {
        "task_duration": {
            "start": "2023-12-10 12:03:02.932571",
            "duration": "0:07:22.956195",
            "radar_time": "2023-12-10 12:00:00",
            "sat_time": null,
            "status": "done",
            "error_msg": null
        }
    },
    {
        "task_duration": {
            "start": "2023-12-10 12:13:02.833069",
            "duration": "0:06:37.547357",
            "radar_time": "2023-12-10 12:10:00",
            "sat_time": null,
            "status": "done",
            "error_msg": null
        }
    },
    {
        "task_duration": {
            "start": "2023-12-10 12:23:02.284391",
            "duration": "0:06:35.767343",
            "radar_time": "2023-12-10 12:20:00",
            "sat_time": null,
            "status": "done",
            "error_msg": null
        }
    },
    {
        "task_duration": {
            "start": "2023-12-10 12:33:03.083195",
            "duration": "0:06:18.506681",
            "radar_time": "2023-12-10 12:30:00",
            "sat_time": null,
            "status": "done",
            "error_msg": null
        }
    },
    {
        "task_duration": {
            "start": "2023-12-10 12:43:02.643039",
            "duration": "0:06:54.256691",
            "radar_time": "2023-12-10 12:40:00",
            "sat_time": null,
            "status": "done",
            "error_msg": null
        }
    },
    {
        "task_duration": {
            "start": "2023-12-10 12:53:02.861704",
            "duration": "0:06:32.100370",
            "radar_time": "2023-12-10 12:50:00",
            "sat_time": null,
            "status": "done",
            "error_msg": null
        }
    },
    {
        "task_duration": {
            "start": "2023-12-10 13:03:02.413956",
            "duration": "0:06:33.942847",
            "radar_time": "2023-12-10 13:00:00",
            "sat_time": null,
            "status": "done",
            "error_msg": null
        }
    },
    {
        "task_duration": {
            "start": "2023-12-10 13:13:02.413467",
            "duration": "0:06:32.198001",
            "radar_time": "2023-12-10 13:10:00",
            "sat_time": null,
            "status": "done",
            "error_msg": null
        }
    },
    {
        "task_duration": {
            "start": "2023-12-10 13:23:02.657049",
            "duration": "0:06:10.292301",
            "radar_time": "2023-12-10 13:20:00",
            "sat_time": null,
            "status": "done",
            "error_msg": null
        }
    },
    {
        "task_duration": {
            "start": "2023-12-10 13:33:03.100887",
            "duration": "0:06:48.147352",
            "radar_time": "2023-12-10 13:30:00",
            "sat_time": null,
            "status": "done",
            "error_msg": null
        }
    },
    {
        "task_duration": {
            "start": "2023-12-10 13:43:03.075882",
            "duration": "0:06:35.146602",
            "radar_time": "2023-12-10 13:40:00",
            "sat_time": null,
            "status": "done",
            "error_msg": null
        }
    },
    {
        "task_duration": {
            "start": "2023-12-10 13:53:02.343212",
            "duration": "0:06:58.018802",
            "radar_time": "2023-12-10 13:50:00",
            "sat_time": null,
            "status": "done",
            "error_msg": null
        }
    },
    {
        "task_duration": {
            "start": "2023-12-10 14:03:02.492449",
            "duration": "0:07:24.019410",
            "radar_time": "2023-12-10 14:00:00",
            "sat_time": null,
            "status": "done",
            "error_msg": null
        }
    },
    {
        "task_duration": {
            "start": "2023-12-10 14:13:02.835421",
            "duration": "0:06:39.691996",
            "radar_time": "2023-12-10 14:10:00",
            "sat_time": null,
            "status": "done",
            "error_msg": null
        }
    },
    {
        "task_duration": {
            "start": "2023-12-10 14:23:02.759873",
            "duration": "0:06:36.767081",
            "radar_time": "2023-12-10 14:20:00",
            "sat_time": null,
            "status": "done",
            "error_msg": null
        }
    },
    {
        "task_duration": {
            "start": "2023-12-10 14:33:02.463322",
            "duration": "0:06:38.304772",
            "radar_time": "2023-12-10 14:30:00",
            "sat_time": null,
            "status": "done",
            "error_msg": null
        }
    },
    {
        "task_duration": {
            "start": "2023-12-10 14:43:02.782782",
            "duration": "0:05:57.566789",
            "radar_time": "2023-12-10 14:40:00",
            "sat_time": "2023-12-10 14:30:00",
            "status": "done",
            "error_msg": "No data found in bounds."
        }
    },
    {
        "task_duration": {
            "start": "2023-12-10 14:53:02.360522",
            "duration": "0:06:56.707039",
            "radar_time": "2023-12-10 14:50:00",
            "sat_time": "2023-12-10 14:40:00",
            "status": "done",
            "error_msg": "No data found in bounds."
        }
    },
    {
        "task_duration": {
            "start": "2023-12-10 15:03:02.511701",
            "duration": "0:06:52.984401",
            "radar_time": "2023-12-10 15:00:00",
            "sat_time": "2023-12-10 14:40:00",
            "status": "done",
            "error_msg": "No data found in bounds."
        }
    },
    {
        "task_duration": {
            "start": "2023-12-10 15:13:02.611937",
            "duration": "0:06:38.909117",
            "radar_time": "2023-12-10 15:10:00",
            "sat_time": "2023-12-10 15:00:00",
            "status": "done",
            "error_msg": "No data found in bounds."
        }
    },
    {
        "task_duration": {
            "start": "2023-12-10 15:23:02.697056",
            "duration": "0:06:00.914222",
            "radar_time": "2023-12-10 15:20:00",
            "sat_time": "2023-12-10 15:10:00",
            "status": "done",
            "error_msg": "No data found in bounds."
        }
    },
    {
        "task_duration": {
            "start": "2023-12-10 15:33:02.747796",
            "duration": "0:07:04.254129",
            "radar_time": "2023-12-10 15:30:00",
            "sat_time": "2023-12-10 15:20:00",
            "status": "done",
            "error_msg": "No data found in bounds."
        }
    },
    {
        "task_duration": {
            "start": "2023-12-10 15:43:02.246660",
            "duration": "0:06:59.025781",
            "radar_time": "2023-12-10 15:40:00",
            "sat_time": "2023-12-10 15:30:00",
            "status": "done",
            "error_msg": "No data found in bounds."
        }
    },
    {
        "task_duration": {
            "start": "2023-12-10 15:53:02.740178",
            "duration": "0:06:29.365677",
            "radar_time": "2023-12-10 15:50:00",
            "sat_time": "2023-12-10 15:40:00",
            "status": "done",
            "error_msg": "No data found in bounds."
        }
    },
    {
        "task_duration": {
            "start": "2023-12-10 16:03:03.050810",
            "duration": "0:05:58.364900",
            "radar_time": "2023-12-10 16:00:00",
            "sat_time": "2023-12-10 15:50:00",
            "status": "done",
            "error_msg": "No data found in bounds."
        }
    },
    {
        "task_duration": {
            "start": "2023-12-10 16:13:02.624379",
            "duration": "0:06:38.995656",
            "radar_time": "2023-12-10 16:10:00",
            "sat_time": "2023-12-10 16:00:00",
            "status": "done",
            "error_msg": "No data found in bounds."
        }
    },
    {
        "task_duration": {
            "start": "2023-12-10 16:23:02.622304",
            "duration": "0:05:27.931713",
            "radar_time": "2023-12-10 16:20:00",
            "sat_time": "2023-12-10 16:10:00",
            "status": "done",
            "error_msg": "No data found in bounds."
        }
    },
    {
        "task_duration": {
            "start": "2023-12-10 16:33:02.604019",
            "duration": "0:06:56.422812",
            "radar_time": "2023-12-10 16:30:00",
            "sat_time": "2023-12-10 16:20:00",
            "status": "done",
            "error_msg": "No data found in bounds."
        }
    },
    {
        "task_duration": {
            "start": "2023-12-10 16:43:03.020409",
            "duration": "0:05:56.411101",
            "radar_time": "2023-12-10 16:40:00",
            "sat_time": "2023-12-10 16:30:00",
            "status": "done",
            "error_msg": "No data found in bounds."
        }
    },
    {
        "task_duration": {
            "start": "2023-12-10 16:53:02.578324",
            "duration": "0:05:57.042313",
            "radar_time": "2023-12-10 16:50:00",
            "sat_time": "2023-12-10 16:40:00",
            "status": "done",
            "error_msg": "No data found in bounds."
        }
    },
    {
        "task_duration": {
            "start": "2023-12-10 17:03:02.616437",
            "duration": "0:06:11.862058",
            "radar_time": "2023-12-10 17:00:00",
            "sat_time": "2023-12-10 16:50:00",
            "status": "done",
            "error_msg": "No data found in bounds."
        }
    },
    {
        "task_duration": {
            "start": "2023-12-10 17:13:02.446778",
            "duration": "0:06:37.563918",
            "radar_time": "2023-12-10 17:10:00",
            "sat_time": "2023-12-10 17:00:00",
            "status": "done",
            "error_msg": "No data found in bounds."
        }
    },
    {
        "task_duration": {
            "start": "2023-12-10 17:23:02.980122",
            "duration": "0:06:17.249676",
            "radar_time": "2023-12-10 17:20:00",
            "sat_time": "2023-12-10 17:10:00",
            "status": "done",
            "error_msg": "No data found in bounds."
        }
    },
    {
        "task_duration": {
            "start": "2023-12-10 17:33:03.145953",
            "duration": "0:05:57.794632",
            "radar_time": "2023-12-10 17:30:00",
            "sat_time": "2023-12-10 17:10:00",
            "status": "done",
            "error_msg": "No data found in bounds."
        }
    },
    {
        "task_duration": {
            "start": "2023-12-10 17:43:02.957714",
            "duration": "0:06:56.445756",
            "radar_time": "2023-12-10 17:40:00",
            "sat_time": "2023-12-10 17:30:00",
            "status": "done",
            "error_msg": "No data found in bounds."
        }
    },
    {
        "task_duration": {
            "start": "2023-12-10 17:53:02.475141",
            "duration": "0:06:00.600642",
            "radar_time": "2023-12-10 17:50:00",
            "sat_time": "2023-12-10 17:40:00",
            "status": "done",
            "error_msg": "No data found in bounds."
        }
    },
    {
        "task_duration": {
            "start": "2023-12-10 18:03:03.080344",
            "duration": "0:06:36.775415",
            "radar_time": "2023-12-10 18:00:00",
            "sat_time": "2023-12-10 17:50:00",
            "status": "done",
            "error_msg": "No data found in bounds."
        }
    },
    {
        "task_duration": {
            "start": "2023-12-10 18:13:02.914438",
            "duration": "0:05:59.577892",
            "radar_time": "2023-12-10 18:10:00",
            "sat_time": "2023-12-10 17:50:00",
            "status": "done",
            "error_msg": "No data found in bounds."
        }
    },
    {
        "task_duration": {
            "start": "2023-12-10 18:23:02.533539",
            "duration": "0:06:26.457322",
            "radar_time": "2023-12-10 18:20:00",
            "sat_time": "2023-12-10 18:10:00",
            "status": "done",
            "error_msg": "No data found in bounds."
        }
    },
    {
        "task_duration": {
            "start": "2023-12-10 18:33:03.120422",
            "duration": "0:05:57.462301",
            "radar_time": "2023-12-10 18:30:00",
            "sat_time": "2023-12-10 18:20:00",
            "status": "done",
            "error_msg": "No data found in bounds."
        }
    },
    {
        "task_duration": {
            "start": "2023-12-10 18:43:02.574853",
            "duration": "0:05:49.753950",
            "radar_time": "2023-12-10 18:40:00",
            "sat_time": "2023-12-10 18:30:00",
            "status": "done",
            "error_msg": "No data found in bounds."
        }
    },
    {
        "task_duration": {
            "start": "2023-12-10 18:53:02.283150",
            "duration": "0:05:57.518994",
            "radar_time": "2023-12-10 18:50:00",
            "sat_time": "2023-12-10 18:40:00",
            "status": "done",
            "error_msg": "No data found in bounds."
        }
    },
    {
        "task_duration": {
            "start": "2023-12-10 19:03:02.745154",
            "duration": "0:06:58.161438",
            "radar_time": "2023-12-10 19:00:00",
            "sat_time": "2023-12-10 18:50:00",
            "status": "done",
            "error_msg": "No data found in bounds."
        }
    },
    {
        "task_duration": {
            "start": "2023-12-10 19:13:02.826993",
            "duration": "0:06:37.928681",
            "radar_time": "2023-12-10 19:10:00",
            "sat_time": "2023-12-10 19:00:00",
            "status": "done",
            "error_msg": "No data found in bounds."
        }
    },
    {
        "task_duration": {
            "start": "2023-12-10 19:23:02.744538",
            "duration": "0:05:27.695399",
            "radar_time": "2023-12-10 19:20:00",
            "sat_time": "2023-12-10 19:10:00",
            "status": "done",
            "error_msg": "No data found in bounds."
        }
    },
    {
        "task_duration": {
            "start": "2023-12-10 19:33:02.331178",
            "duration": "0:06:20.386634",
            "radar_time": "2023-12-10 19:30:00",
            "sat_time": "2023-12-10 19:20:00",
            "status": "done",
            "error_msg": "No data found in bounds."
        }
    },
    {
        "task_duration": {
            "start": "2023-12-10 19:43:02.648043",
            "duration": "0:05:23.302463",
            "radar_time": "2023-12-10 19:40:00",
            "sat_time": "2023-12-10 19:30:00",
            "status": "done",
            "error_msg": "No data found in bounds."
        }
    },
    {
        "task_duration": {
            "start": "2023-12-10 19:53:02.701209",
            "duration": "0:06:36.772377",
            "radar_time": "2023-12-10 19:50:00",
            "sat_time": "2023-12-10 19:40:00",
            "status": "done",
            "error_msg": "No data found in bounds."
        }
    },
    {
        "task_duration": {
            "start": "2023-12-10 20:03:02.443256",
            "duration": "0:07:22.803001",
            "radar_time": "2023-12-10 20:00:00",
            "sat_time": "2023-12-10 19:50:00",
            "status": "done",
            "error_msg": "No data found in bounds."
        }
    },
    {
        "task_duration": {
            "start": "2023-12-10 20:13:02.290250",
            "duration": "0:05:59.061258",
            "radar_time": "2023-12-10 20:10:00",
            "sat_time": "2023-12-10 20:00:00",
            "status": "done",
            "error_msg": "No data found in bounds."
        }
    },
    {
        "task_duration": {
            "start": "2023-12-10 20:23:02.323784",
            "duration": "0:06:34.364789",
            "radar_time": "2023-12-10 20:20:00",
            "sat_time": "2023-12-10 20:10:00",
            "status": "done",
            "error_msg": "No data found in bounds."
        }
    },
    {
        "task_duration": {
            "start": "2023-12-10 20:33:02.581344",
            "duration": "0:06:04.750851",
            "radar_time": "2023-12-10 20:30:00",
            "sat_time": "2023-12-10 20:20:00",
            "status": "done",
            "error_msg": "No data found in bounds."
        }
    },
    {
        "task_duration": {
            "start": "2023-12-10 20:43:02.196166",
            "duration": "0:06:38.804234",
            "radar_time": "2023-12-10 20:40:00",
            "sat_time": "2023-12-10 20:30:00",
            "status": "done",
            "error_msg": "No data found in bounds."
        }
    },
    {
        "task_duration": {
            "start": "2023-12-10 20:53:02.915419",
            "duration": "0:06:56.354436",
            "radar_time": "2023-12-10 20:50:00",
            "sat_time": "2023-12-10 20:40:00",
            "status": "done",
            "error_msg": "No data found in bounds."
        }
    },
    {
        "task_duration": {
            "start": "2023-12-10 21:03:02.369963",
            "duration": "0:06:00.376083",
            "radar_time": "2023-12-10 21:00:00",
            "sat_time": "2023-12-10 20:50:00",
            "status": "done",
            "error_msg": "No data found in bounds."
        }
    },
    {
        "task_duration": {
            "start": "2023-12-10 21:13:02.657737",
            "duration": "0:06:00.532425",
            "radar_time": "2023-12-10 21:10:00",
            "sat_time": "2023-12-10 21:00:00",
            "status": "done",
            "error_msg": "No data found in bounds."
        }
    },
    {
        "task_duration": {
            "start": "2023-12-10 21:23:03.176027",
            "duration": "0:05:57.776468",
            "radar_time": "2023-12-10 21:20:00",
            "sat_time": "2023-12-10 21:10:00",
            "status": "done",
            "error_msg": "No data found in bounds."
        }
    },
    {
        "task_duration": {
            "start": "2023-12-10 21:33:02.863214",
            "duration": "0:07:18.508230",
            "radar_time": "2023-12-10 21:30:00",
            "sat_time": "2023-12-10 21:20:00",
            "status": "done",
            "error_msg": "No data found in bounds."
        }
    },
    {
        "task_duration": {
            "start": "2023-12-10 21:43:02.299560",
            "duration": "0:06:14.977537",
            "radar_time": "2023-12-10 21:40:00",
            "sat_time": "2023-12-10 21:30:00",
            "status": "done",
            "error_msg": "No data found in bounds."
        }
    },
    {
        "task_duration": {
            "start": "2023-12-10 21:53:03.133324",
            "duration": "0:05:47.628447",
            "radar_time": "2023-12-10 21:50:00",
            "sat_time": "2023-12-10 21:40:00",
            "status": "done",
            "error_msg": "No data found in bounds."
        }
    },
    {
        "task_duration": {
            "start": "2023-12-10 22:03:02.741454",
            "duration": "0:07:25.190590",
            "radar_time": "2023-12-10 22:00:00",
            "sat_time": "2023-12-10 21:50:00",
            "status": "done",
            "error_msg": "No data found in bounds."
        }
    },
    {
        "task_duration": {
            "start": "2023-12-10 22:13:02.913175",
            "duration": "0:06:01.429553",
            "radar_time": "2023-12-10 22:10:00",
            "sat_time": "2023-12-10 22:00:00",
            "status": "done",
            "error_msg": "No data found in bounds."
        }
    },
    {
        "task_duration": {
            "start": "2023-12-10 22:23:02.276290",
            "duration": "0:06:57.725117",
            "radar_time": "2023-12-10 22:20:00",
            "sat_time": null,
            "status": "done",
            "error_msg": null
        }
    },
    {
        "task_duration": {
            "start": "2023-12-10 22:33:02.715794",
            "duration": "0:06:57.607384",
            "radar_time": "2023-12-10 22:30:00",
            "sat_time": null,
            "status": "done",
            "error_msg": null
        }
    },
    {
        "task_duration": {
            "start": "2023-12-10 22:43:02.223299",
            "duration": "0:06:38.196409",
            "radar_time": "2023-12-10 22:40:00",
            "sat_time": null,
            "status": "done",
            "error_msg": null
        }
    },
    {
        "task_duration": {
            "start": "2023-12-10 22:53:02.350415",
            "duration": "0:06:51.613222",
            "radar_time": "2023-12-10 22:50:00",
            "sat_time": null,
            "status": "done",
            "error_msg": null
        }
    },
    {
        "task_duration": {
            "start": "2023-12-10 23:03:02.900365",
            "duration": "0:06:33.115519",
            "radar_time": "2023-12-10 23:00:00",
            "sat_time": null,
            "status": "done",
            "error_msg": null
        }
    },
    {
        "task_duration": {
            "start": "2023-12-10 23:13:02.837338",
            "duration": "0:06:55.716256",
            "radar_time": "2023-12-10 23:10:00",
            "sat_time": null,
            "status": "done",
            "error_msg": null
        }
    },
    {
        "task_duration": {
            "start": "2023-12-10 23:23:02.421258",
            "duration": "0:06:57.300570",
            "radar_time": "2023-12-10 23:20:00",
            "sat_time": null,
            "status": "done",
            "error_msg": null
        }
    },
    {
        "task_duration": {
            "start": "2023-12-10 23:33:02.621594",
            "duration": "0:06:25.452839",
            "radar_time": "2023-12-10 23:30:00",
            "sat_time": null,
            "status": "done",
            "error_msg": null
        }
    },
    {
        "task_duration": {
            "start": "2023-12-10 23:43:03.011783",
            "duration": "0:06:35.623286",
            "radar_time": "2023-12-10 23:40:00",
            "sat_time": null,
            "status": "done",
            "error_msg": null
        }
    },
    {
        "task_duration": {
            "start": "2023-12-10 23:53:02.539179",
            "duration": "0:06:52.442472",
            "radar_time": "2023-12-10 23:50:00",
            "sat_time": null,
            "status": "done",
            "error_msg": null
        }
    }
]